deasync.py
deasync-1.0.1.dist-info/DESCRIPTION.rst
deasync-1.0.1.dist-info/METADATA
deasync-1.0.1.dist-info/RECORD
deasync-1.0.1.dist-info/WHEEL
deasync-1.0.1.dist-info/metadata.json
deasync-1.0.1.dist-info/top_level.txt
