Metadata-Version: 2.0
Name: deasync
Version: 1.0.1
Summary: deasync decorator to make async functions/methods synchronous.
Home-page: https://github.com/prokopst/deasync
Author: Stanislav Prokop
Author-email: UNKNOWN
License: MIT
Keywords: async await deasync desynchronize
Platform: UNKNOWN
Classifier: Development Status :: 4 - Beta
Classifier: Intended Audience :: Developers
Classifier: Topic :: Software Development :: Libraries
Classifier: License :: OSI Approved :: MIT License
Classifier: Programming Language :: Python :: 3.5
